Metadata-Version: 1.0
Name: JobsGe
Version: 0.2
Summary: Rest api for jobs.ge
Home-page: UNKNOWN
Author: Goga Patarkatsishvili
Author-email: ent1c3d@gmail.com
License: MIT
Platform: UNKNOWN
